odoo/addons/l10n_it_withholding_tax_payment_order/README.rst
odoo/addons/l10n_it_withholding_tax_payment_order/__init__.py
odoo/addons/l10n_it_withholding_tax_payment_order/__manifest__.py
odoo/addons/l10n_it_withholding_tax_payment_order/i18n/it.po
odoo/addons/l10n_it_withholding_tax_payment_order/i18n/l10n_it_withholding_tax_payment_order.pot
odoo/addons/l10n_it_withholding_tax_payment_order/models/__init__.py
odoo/addons/l10n_it_withholding_tax_payment_order/models/account_move_line.py
odoo/addons/l10n_it_withholding_tax_payment_order/readme/CONTRIBUTORS.md
odoo/addons/l10n_it_withholding_tax_payment_order/readme/DESCRIPTION.md
odoo/addons/l10n_it_withholding_tax_payment_order/static/description/icon.png
odoo/addons/l10n_it_withholding_tax_payment_order/static/description/index.html
odoo_addon_l10n_it_withholding_tax_payment_order-16.0.1.0.0.4.dist-info/METADATA
odoo_addon_l10n_it_withholding_tax_payment_order-16.0.1.0.0.4.dist-info/WHEEL
odoo_addon_l10n_it_withholding_tax_payment_order-16.0.1.0.0.4.dist-info/top_level.txt
odoo_addon_l10n_it_withholding_tax_payment_order-16.0.1.0.0.4.dist-info/RECORD
